[
  {
    "id": "f67a3737-63d2-414f-a610-5ac5c35eaa36",
    "data": [
      {
        "text": "Say something",
        "userDefined": false
      }
    ],
    "isTemplate": false,
    "count": 0
  },
  {
    "id": "7b2f0927-82c7-4825-a9b6-5b04e4a921bc",
    "data": [
      {
        "text": "Tell me something",
        "userDefined": false
      }
    ],
    "isTemplate": false,
    "count": 0
  },
  {
    "id": "5b3d4bfb-6fe8-42b0-b2a6-176bcb08e11a",
    "data": [
      {
        "text": "Say something about you",
        "userDefined": false
      }
    ],
    "isTemplate": false,
    "count": 0
  },
  {
    "id": "a09500b6-b6f2-44be-9cd9-cdd84ce85ebb",
    "data": [
      {
        "text": "Tell me about yourself",
        "userDefined": false
      }
    ],
    "isTemplate": false,
    "count": 0
  }
]